compspace/__init__.py
compspace/animation.py
compspace/axes_2d.py
compspace/axes_3d.py
compspace/containers.py
compspace/convenience.py
compspace/utility.py
compspace-0.0.6.dist-info/licenses/LICENSE
compspace-0.0.6.dist-info/METADATA
compspace-0.0.6.dist-info/WHEEL
compspace-0.0.6.dist-info/top_level.txt
compspace-0.0.6.dist-info/RECORD
