Metadata-Version: 2.4
Name: compspace
Version: 0.0.6
Summary: A matplotlib-based plotting library for visualizing composition spaces.
Author-email: Felix Thelen <felix.thelen@ruhr-uni-bochum.de>
License: 
Project-URL: Repository, https://github.com/felixthln/simplices
Keywords: materials science,composition spaces,chemistry,matplotlib
Classifier: Intended Audience :: Science/Research
Classifier: Natural Language :: English
Classifier: Programming Language :: Python
Classifier: Operating System :: Microsoft :: Windows
Classifier: Programming Language :: Python :: 3
Classifier: Programming Language :: Python :: 3.9
Classifier: Programming Language :: Python :: 3.10
Classifier: Programming Language :: Python :: 3.11
Classifier: Programming Language :: Python :: 3.12
Requires-Python: >=3.9
License-File: LICENSE
Requires-Dist: numpy>=1.26.0
Requires-Dist: pandas>=2.1.1
Requires-Dist: matplotlib>=3.1.0
Requires-Dist: ffmpeg-python>=0.2.0
Dynamic: license-file
